{
  "project_info": {
    "project_number": "697478237599",
    "firebase_url": "https://mini-games-multiplayer-app-default-rtdb.europe-west1.firebasedatabase.app",
    "project_id": "mini-games-multiplayer-app",
    "storage_bucket": "mini-games-multiplayer-app.firebasestorage.app"
  },
  "client": [
    {
      "client_info": {
        "mobilesdk_app_id": "1:697478237599:android:5064ca90ccc7285f5d41aa",
        "android_client_info": {
          "package_name": "com.Elvin.MultiplayerMiniGames"
        }
      },
      "oauth_client": [],
      "api_key": [
        {
          "current_key": "AIzaSyCZoopzwRs8U-b1hYAlH-5AJoHDI7win44"
        }
      ],
      "services": {
        "appinvite_service": {
          "other_platform_oauth_client": []
        }
      }
    }
  ],
  "configuration_version": "1"
}